functionalOAI/__init__.py
functionalOAI/funAI.py
functionalOAI/functions.py
funcOAI-0.0.4.dist-info/LICENSE
funcOAI-0.0.4.dist-info/METADATA
funcOAI-0.0.4.dist-info/WHEEL
funcOAI-0.0.4.dist-info/top_level.txt
funcOAI-0.0.4.dist-info/RECORD
