Metadata-Version: 2.1
Name: funcOAI
Version: 0.0.4
Summary: A package that helps users easily create functions to feed to GPT function calling API
Home-page: UNKNOWN
Author: x5up0 aka.ryan
Author-email: x5up0sbu@gmail.com
License: UNKNOWN
Keywords: python,OpenAI,ChatGPT,GPT API,function calling API,functions,openai-gpt
Platform: UNKNOWN
Classifier: Development Status :: 5 - Production/Stable
Classifier: Intended Audience :: Developers
Classifier: Programming Language :: Python :: 3
Classifier: Operating System :: Unix
Classifier: Operating System :: MacOS :: MacOS X
Classifier: Operating System :: Microsoft :: Windows
License-File: LICENSE
